{"hdr":"MONDIALE 120","overview":"ПРЕСС-ПОДБОРЩИК С КАМЕРОЙ ФИКСИРОВАННОГО ОБЪЕМА \r\rМодель MONDIALE 120 Маскио-Гаспардо сочетает в себе надежность и  технологические решения, характеризующие модели более высокого диапазона, с удобством и простотой рулонных пресс-подборщиков с камерой фиксированного объема. Благодаря наличию открываемого днища, централизованной системы смазки, высокоэффективной системы увязки и удобного монитора электрического управления данная машина представляет собой высокопроизводительную профессиональную модель.\r","techHdrs":["ВЕРСИЯ","1-1.png","1-2.png","1-3.png","1-4.png","1-6.png"],"tech0":["120 TOPCUT","220","120","102"],"tech1":["120 ULTRACUT","220","120","102"],"std":["Техническая информация","стандартное оборудование","Особенности","широкий подборщик","фиксированная камера","диаметр рулона 1200 мм","ширина рулона 1200 мм","двойная нить","сеть","автоматическая центральная смазка","счетчик рулонов","колеса 400/60","15 ножей","широкий подборщик","фиксированная камера","диаметр рулона 1200 мм","ширина рулона 1200 мм","двойная нить","сеть","автоматическая центральная смазка","счетчик рулонов","колеса 400/60","25 ножей: большое количество ножей позволяет осуществлять резку сена на 45 и 90 мм","Tamburo del pick-up a basso profilo. I denti dell'infaldatore raggiungono l'andana da sotto per alzare - non spingere - il prodotto nell'apertura della camera. ","Il suo design compatto e la posizione regolabile dei denti evitano una \"zona d'ombra\" di prodotto fra i denti ed il rotore.","La sicurezza a bullone di trancio previene danneggiamenti derivanti dall'sovraccarico del sistema di alimentazione.","Il sistema flottante idraulico del pick-up assicura una raccolta omogenea e senza residui."],"access":[],"picts":["79-0.jpg","79-1.jpg","79-2.jpg"]}