{"hdr":"MONDIALE 120 COMBI","overview":"КОМБИНИРОВАННЫЙ ПРЕСС-ПОДБОРЩИК С ВАЛЬЦАМИ И РОТОРНЫМ УКЛАДЧИКОМ\r\rMONDIALE 120 COMBI - представляет собой универсальную машину для работы с сеном и сенажом. \rБлагодаря комбинации \"пресс-подборщик - упаковщик\" материал собирается, прессуется и упаковывается в пленку на одной машине! При этом материал не контактирует с почвой, не загрязняется и, благодаря мгновенной упаковке, хранится уже без риска порчи из-за неблагоприятной погоды. За 1 проход машина выполняет все задачи по кормозаготовке, что, как следствие, приводит к экономии времени и уменьшению расхода топлива - бесспорные экономические выгоды для любого хозяйства.\r\rMONDIALE 120 COMBI оснащен обмотчиком ON LINER PRO, который состоит из платформы с тремя роликами и двух автоматически контролируемых растяжителей пленки.","techHdrs":["ВЕРСИЯ","1-1.png","1-2.png","1-3.png","1-4.png","1-6.png"],"tech0":["120 COMBI TOPCUT","80 / 110","2200","1200","15","1200"],"tech1":["120 COMBI ULTRACUT","95 / 130","2200","1200","25","1200"],"std":["Техническая информация","стандартное оборудование","широкий подборщик","фиксированная камера","диаметр рулона 1200 мм","ширина рулона 1200 мм","двойная нить","сеть","автоматическая центральная смазка"," счетчик рулонов","колеса 600","выгрузочная рампа ","дополнительный держатель рулона"," 15 ножей","широкий подборщик","фиксированная камера","диаметр рулона 1200 мм","ширина рулона 1200 мм","двойная нить","сеть","автоматическая центральная смазка","счетчик рулонов","колеса 600","выгрузочная рампа","дополнительный держатель рулона","25 ножей"],"access":[],"picts":["80-0.jpg","80-1.jpg","80-2.jpg","80-3.jpg","80-4.jpg","80-5.jpg","80-6.jpg","80-7.jpg","80-8.jpg","80-9.jpg","80-10.jpg","80-11.jpg","80-12.jpg"]}